[
    {
        "dx": 44,
        "dy": 14,
        "index": 1
    },
    {
        "dx": 47,
        "dy": 50,
        "index": 2
    },
    {
        "dx": 47,
        "dy": 71,
        "index": 3
    },
    {
        "dx": 47,
        "dy": 105,
        "index": 4
    },
    {
        "dx": 47,
        "dy": 130,
        "index": 5
    },
    {
        "dx": 46,
        "dy": 151,
        "index": 6
    },
    {
        "dx": 46,
        "dy": 186,
        "index": 7
    },
    {
        "dx": 48,
        "dy": 206,
        "index": 8
    },
    {
        "dx": 52,
        "dy": 233,
        "index": 9
    },
    {
        "dx": 49,
        "dy": 265,
        "index": 10
    },
    {
        "dx": 48,
        "dy": 291,
        "index": 11
    },
    {
        "dx": 48,
        "dy": 324,
        "index": 12
    },
    {
        "dx": 51,
        "dy": 359,
        "index": 13
    },
    {
        "dx": 51,
        "dy": 384,
        "index": 14
    },
    {
        "dx": 51,
        "dy": 414,
        "index": 15
    },
    {
        "dx": 53,
        "dy": 440,
        "index": 16
    },
    {
        "dx": 52,
        "dy": 473,
        "index": 17
    }
]